<OpenSearchDescription xmlns="http://a9.com/-/spec/opensearch/1.1/"
                       xmlns:moz="http://www.mozilla.org/2006/browser/search/">
<ShortName>Twitter</ShortName>
<Description>Twitter Search</Description>
<InputEncoding>UTF-8</InputEncoding>
<Image width="16" height="16">http://search.twitter.com/favicon.png</Image>
<Url type="text/html" method="GET" template="http://search.twitter.com/search?q={searchTerms}"/>
<moz:SearchForm>http://search.twitter.com/</moz:SearchForm>
</OpenSearchDescription>

